anmi/__init__.py
anmi/T2/__init__.py
anmi/T2/funcs_LUD.py
anmi/T2/funcs_gram_schmidt.py
anmi/T2/funcs_householder_QR.py
anmi/T2/funcs_met_iters.py
anmi/T3/__init__.py
anmi/T4/__init__.py
anmi/T4/funcs_aproximacion.py
anmi/T4/funcs_bernstein.py
anmi/T4/funcs_fourier.py
anmi/T4/funcs_ruffini.py
anmi/T5/__init__.py
anmi/T6/__init__.py
anmi/T6/funcs_derivadas.py
anmi/T6/funcs_integrales.py
anmi/genericas/__init__.py
anmi-0.0.6.dist-info/LICENSE
anmi-0.0.6.dist-info/METADATA
anmi-0.0.6.dist-info/WHEEL
anmi-0.0.6.dist-info/top_level.txt
anmi-0.0.6.dist-info/RECORD
