Metadata-Version: 2.1
Name: anmi
Version: 0.0.6
Summary: Archivos para correr ANMI
Home-page: https://github.com/alexmascension/ANMI
Author: alexmascension
Author-email: alexmascension@gmail.com
License: UNKNOWN
Project-URL: Bug Tracker, https://github.com/alexmascension/ANMI/issues
Platform: UNKNOWN
Classifier: Programming Language :: Python :: 3
Classifier: License :: OSI Approved :: BSD License
Classifier: Operating System :: OS Independent
Requires-Python: >=3.6
